<annotation>
	<folder></folder>
	<filename>000000000389_jpg.rf.1dd437dbb518e480b21652cf552e5b2d.jpg</filename>
	<path>000000000389_jpg.rf.1dd437dbb518e480b21652cf552e5b2d.jpg</path>
	<source>
		<database>roboflow.ai</database>
	</source>
	<size>
		<width>640</width>
		<height>640</height>
		<depth>3</depth>
	</size>
	<segmented>0</segmented>
	<object>
		<name>tie</name>
		<pose>Unspecified</pose>
		<truncated>0</truncated>
		<difficult>0</difficult>
		<occluded>0</occluded>
		<bndbox>
			<xmin>308</xmin>
			<xmax>374</xmax>
			<ymin>402</ymin>
			<ymax>640</ymax>
		</bndbox>
	</object>
	<object>
		<name>person</name>
		<pose>Unspecified</pose>
		<truncated>0</truncated>
		<difficult>0</difficult>
		<occluded>0</occluded>
		<bndbox>
			<xmin>1</xmin>
			<xmax>142</xmax>
			<ymin>344</ymin>
			<ymax>640</ymax>
		</bndbox>
	</object>
	<object>
		<name>person</name>
		<pose>Unspecified</pose>
		<truncated>0</truncated>
		<difficult>0</difficult>
		<occluded>0</occluded>
		<bndbox>
			<xmin>468</xmin>
			<xmax>567</xmax>
			<ymin>390</ymin>
			<ymax>640</ymax>
		</bndbox>
	</object>
	<object>
		<name>person</name>
		<pose>Unspecified</pose>
		<truncated>0</truncated>
		<difficult>0</difficult>
		<occluded>0</occluded>
		<bndbox>
			<xmin>92</xmin>
			<xmax>184</xmax>
			<ymin>334</ymin>
			<ymax>562</ymax>
		</bndbox>
	</object>
	<object>
		<name>person</name>
		<pose>Unspecified</pose>
		<truncated>0</truncated>
		<difficult>0</difficult>
		<occluded>0</occluded>
		<bndbox>
			<xmin>568</xmin>
			<xmax>640</xmax>
			<ymin>361</ymin>
			<ymax>529</ymax>
		</bndbox>
	</object>
	<object>
		<name>person</name>
		<pose>Unspecified</pose>
		<truncated>0</truncated>
		<difficult>0</difficult>
		<occluded>0</occluded>
		<bndbox>
			<xmin>43</xmin>
			<xmax>57</xmax>
			<ymin>232</ymin>
			<ymax>290</ymax>
		</bndbox>
	</object>
	<object>
		<name>person</name>
		<pose>Unspecified</pose>
		<truncated>0</truncated>
		<difficult>0</difficult>
		<occluded>0</occluded>
		<bndbox>
			<xmin>172</xmin>
			<xmax>220</xmax>
			<ymin>382</ymin>
			<ymax>444</ymax>
		</bndbox>
	</object>
	<object>
		<name>person</name>
		<pose>Unspecified</pose>
		<truncated>0</truncated>
		<difficult>0</difficult>
		<occluded>0</occluded>
		<bndbox>
			<xmin>431</xmin>
			<xmax>474</xmax>
			<ymin>345</ymin>
			<ymax>409</ymax>
		</bndbox>
	</object>
	<object>
		<name>person</name>
		<pose>Unspecified</pose>
		<truncated>0</truncated>
		<difficult>0</difficult>
		<occluded>0</occluded>
		<bndbox>
			<xmin>395</xmin>
			<xmax>428</xmax>
			<ymin>324</ymin>
			<ymax>360</ymax>
		</bndbox>
	</object>
	<object>
		<name>person</name>
		<pose>Unspecified</pose>
		<truncated>0</truncated>
		<difficult>0</difficult>
		<occluded>0</occluded>
		<bndbox>
			<xmin>563</xmin>
			<xmax>640</xmax>
			<ymin>497</ymin>
			<ymax>640</ymax>
		</bndbox>
	</object>
	<object>
		<name>backpack</name>
		<pose>Unspecified</pose>
		<truncated>0</truncated>
		<difficult>0</difficult>
		<occluded>0</occluded>
		<bndbox>
			<xmin>387</xmin>
			<xmax>465</xmax>
			<ymin>356</ymin>
			<ymax>640</ymax>
		</bndbox>
	</object>
	<object>
		<name>person</name>
		<pose>Unspecified</pose>
		<truncated>0</truncated>
		<difficult>0</difficult>
		<occluded>0</occluded>
		<bndbox>
			<xmin>142</xmin>
			<xmax>510</xmax>
			<ymin>113</ymin>
			<ymax>633</ymax>
		</bndbox>
	</object>
	<object>
		<name>person</name>
		<pose>Unspecified</pose>
		<truncated>0</truncated>
		<difficult>0</difficult>
		<occluded>0</occluded>
		<bndbox>
			<xmin>519</xmin>
			<xmax>527</xmax>
			<ymin>361</ymin>
			<ymax>374</ymax>
		</bndbox>
	</object>
	<object>
		<name>person</name>
		<pose>Unspecified</pose>
		<truncated>0</truncated>
		<difficult>0</difficult>
		<occluded>0</occluded>
		<bndbox>
			<xmin>518</xmin>
			<xmax>592</xmax>
			<ymin>361</ymin>
			<ymax>556</ymax>
		</bndbox>
	</object>
</annotation>
