<annotation>
	<folder></folder>
	<filename>000000000514_jpg.rf.b65ef17c163528ff0f3c2131fd346a51.jpg</filename>
	<path>000000000514_jpg.rf.b65ef17c163528ff0f3c2131fd346a51.jpg</path>
	<source>
		<database>roboflow.ai</database>
	</source>
	<size>
		<width>640</width>
		<height>640</height>
		<depth>3</depth>
	</size>
	<segmented>0</segmented>
	<object>
		<name>bed</name>
		<pose>Unspecified</pose>
		<truncated>0</truncated>
		<difficult>0</difficult>
		<occluded>0</occluded>
		<bndbox>
			<xmin>67</xmin>
			<xmax>639</xmax>
			<ymin>227</ymin>
			<ymax>626</ymax>
		</bndbox>
	</object>
</annotation>
